herokutokenizer/__init__.py
herokutokenizer-0.0.1.dist-info/LICENSE
herokutokenizer-0.0.1.dist-info/METADATA
herokutokenizer-0.0.1.dist-info/WHEEL
herokutokenizer-0.0.1.dist-info/top_level.txt
herokutokenizer-0.0.1.dist-info/RECORD
