Metadata-Version: 2.1
Name: herokutokenizer
Version: 0.0.1
Summary: Tokenizer And Starting Verb Extractor For Heroku Flask Project
Home-page: UNKNOWN
Author: Siddhant Sarkar
Author-email: siddhant.gecbilaspur@gmail.com
License: UNKNOWN
Platform: UNKNOWN
Classifier: Programming Language :: Python :: 3
Classifier: License :: OSI Approved :: MIT License
Classifier: Operating System :: OS Independent
Requires-Python: >=3.6
